{
  "id": "00000000-0000-0000-0000-000000000000",
  "prevId": "",
  "version": "7",
  "dialect": "postgresql",
  "tables": {
    "public.schema_migrations": {
      "name": "schema_migrations",
      "schema": "",
      "columns": {
        "version": {
          "name": "version",
          "type": "bigint",
          "primaryKey": true,
          "notNull": true
        },
        "inserted_at": {
          "name": "inserted_at",
          "type": "timestamp(0)",
          "primaryKey": false,
          "notNull": false
        }
      },
      "indexes": {},
      "foreignKeys": {},
      "compositePrimaryKeys": {},
      "uniqueConstraints": {},
      "checkConstraints": {},
      "policies": {},
      "isRLSEnabled": false
    },
    "public.jobs": {
      "name": "jobs",
      "schema": "",
      "columns": {
        "id": {
          "name": "id",
          "type": "uuid",
          "primaryKey": true,
          "notNull": true,
          "default": "gen_random_uuid()"
        },
        "external_id": {
          "name": "external_id",
          "type": "varchar(255)",
          "primaryKey": false,
          "notNull": true
        },
        "title": {
          "name": "title",
          "type": "varchar(255)",
          "primaryKey": false,
          "notNull": true
        },
        "company": {
          "name": "company",
          "type": "varchar(255)",
          "primaryKey": false,
          "notNull": false
        },
        "salary": {
          "name": "salary",
          "type": "varchar(255)",
          "primaryKey": false,
          "notNull": false
        },
        "area": {
          "name": "area",
          "type": "varchar(255)",
          "primaryKey": false,
          "notNull": false
        },
        "url": {
          "name": "url",
          "type": "text",
          "primaryKey": false,
          "notNull": false
        },
        "description": {
          "name": "description",
          "type": "text",
          "primaryKey": false,
          "notNull": false
        },
        "source": {
          "name": "source",
          "type": "varchar(255)",
          "primaryKey": false,
          "notNull": false,
          "default": "'hh.ru'"
        },
        "search_query": {
          "name": "search_query",
          "type": "varchar(255)",
          "primaryKey": false,
          "notNull": false
        },
        "fetched_at": {
          "name": "fetched_at",
          "type": "timestamp(0)",
          "primaryKey": false,
          "notNull": false
        },
        "inserted_at": {
          "name": "inserted_at",
          "type": "timestamp(0)",
          "primaryKey": false,
          "notNull": true
        },
        "updated_at": {
          "name": "updated_at",
          "type": "timestamp(0)",
          "primaryKey": false,
          "notNull": true
        },
        "hh_vacancy_id": {
          "name": "hh_vacancy_id",
          "type": "varchar(255)",
          "primaryKey": false,
          "notNull": false
        },
        "has_test": {
          "name": "has_test",
          "type": "boolean",
          "primaryKey": false,
          "notNull": true,
          "default": false
        },
        "test_required": {
          "name": "test_required",
          "type": "boolean",
          "primaryKey": false,
          "notNull": true,
          "default": false
        },
        "employer_id": {
          "name": "employer_id",
          "type": "varchar(255)",
          "primaryKey": false,
          "notNull": false
        },
        "skills": {
          "name": "skills",
          "type": "varchar(255)[]",
          "primaryKey": false,
          "notNull": false,
          "default": "'{\"RAY\"}'"
        }
      },
      "indexes": {
        "jobs_external_id_index": {
          "name": "jobs_external_id_index",
          "columns": [
            {
              "expression": "external_id",
              "asc": true,
              "nulls": "last",
              "opclass": "text_ops",
              "isExpression": false
            }
          ],
          "isUnique": true,
          "concurrently": false,
          "method": "btree",
          "with": {}
        },
        "jobs_fetched_at_index": {
          "name": "jobs_fetched_at_index",
          "columns": [
            {
              "expression": "fetched_at",
              "asc": true,
              "nulls": "last",
              "opclass": "timestamp_ops",
              "isExpression": false
            }
          ],
          "isUnique": false,
          "concurrently": false,
          "method": "btree",
          "with": {}
        },
        "jobs_hh_vacancy_id_index": {
          "name": "jobs_hh_vacancy_id_index",
          "columns": [
            {
              "expression": "hh_vacancy_id",
              "asc": true,
              "nulls": "last",
              "opclass": "text_ops",
              "isExpression": false
            }
          ],
          "isUnique": true,
          "concurrently": false,
          "method": "btree",
          "with": {}
        },
        "jobs_source_index": {
          "name": "jobs_source_index",
          "columns": [
            {
              "expression": "source",
              "asc": true,
              "nulls": "last",
              "opclass": "text_ops",
              "isExpression": false
            }
          ],
          "isUnique": false,
          "concurrently": false,
          "method": "btree",
          "with": {}
        }
      },
      "foreignKeys": {},
      "compositePrimaryKeys": {},
      "uniqueConstraints": {},
      "checkConstraints": {},
      "policies": {},
      "isRLSEnabled": false
    },
    "public.applications": {
      "name": "applications",
      "schema": "",
      "columns": {
        "id": {
          "name": "id",
          "type": "uuid",
          "primaryKey": true,
          "notNull": true,
          "default": "gen_random_uuid()"
        },
        "user_id": {
          "name": "user_id",
          "type": "uuid",
          "primaryKey": false,
          "notNull": true
        },
        "job_id": {
          "name": "job_id",
          "type": "uuid",
          "primaryKey": false,
          "notNull": false
        },
        "job_external_id": {
          "name": "job_external_id",
          "type": "varchar(255)",
          "primaryKey": false,
          "notNull": true
        },
        "cover_letter": {
          "name": "cover_letter",
          "type": "text",
          "primaryKey": false,
          "notNull": false
        },
        "status": {
          "name": "status",
          "type": "varchar(255)",
          "primaryKey": false,
          "notNull": false,
          "default": "'pending'"
        },
        "submitted_at": {
          "name": "submitted_at",
          "type": "timestamp(0)",
          "primaryKey": false,
          "notNull": false
        },
        "response_data": {
          "name": "response_data",
          "type": "jsonb",
          "primaryKey": false,
          "notNull": false
        },
        "error_message": {
          "name": "error_message",
          "type": "text",
          "primaryKey": false,
          "notNull": false
        },
        "hh_resume_id": {
          "name": "hh_resume_id",
          "type": "varchar(255)",
          "primaryKey": false,
          "notNull": false
        },
        "inserted_at": {
          "name": "inserted_at",
          "type": "timestamp(0)",
          "primaryKey": false,
          "notNull": true
        },
        "updated_at": {
          "name": "updated_at",
          "type": "timestamp(0)",
          "primaryKey": false,
          "notNull": true
        },
        "hh_negotiation_id": {
          "name": "hh_negotiation_id",
          "type": "varchar(255)",
          "primaryKey": false,
          "notNull": false
        },
        "hh_status": {
          "name": "hh_status",
          "type": "varchar(255)",
          "primaryKey": false,
          "notNull": false
        },
        "rate_limited_until": {
          "name": "rate_limited_until",
          "type": "timestamp(0)",
          "primaryKey": false,
          "notNull": false
        }
      },
      "indexes": {
        "applications_job_id_index": {
          "name": "applications_job_id_index",
          "columns": [
            {
              "expression": "job_id",
              "asc": true,
              "nulls": "last",
              "opclass": "uuid_ops",
              "isExpression": false
            }
          ],
          "isUnique": false,
          "concurrently": false,
          "method": "btree",
          "with": {}
        },
        "applications_status_index": {
          "name": "applications_status_index",
          "columns": [
            {
              "expression": "status",
              "asc": true,
              "nulls": "last",
              "opclass": "text_ops",
              "isExpression": false
            }
          ],
          "isUnique": false,
          "concurrently": false,
          "method": "btree",
          "with": {}
        },
        "applications_submitted_at_index": {
          "name": "applications_submitted_at_index",
          "columns": [
            {
              "expression": "submitted_at",
              "asc": true,
              "nulls": "last",
              "opclass": "timestamp_ops",
              "isExpression": false
            }
          ],
          "isUnique": false,
          "concurrently": false,
          "method": "btree",
          "with": {}
        },
        "applications_user_id_index": {
          "name": "applications_user_id_index",
          "columns": [
            {
              "expression": "user_id",
              "asc": true,
              "nulls": "last",
              "opclass": "uuid_ops",
              "isExpression": false
            }
          ],
          "isUnique": false,
          "concurrently": false,
          "method": "btree",
          "with": {}
        }
      },
      "foreignKeys": {
        "applications_user_id_fkey": {
          "name": "applications_user_id_fkey",
          "tableFrom": "applications",
          "tableTo": "users",
          "schemaTo": "public",
          "columnsFrom": [
            "user_id"
          ],
          "columnsTo": [
            "id"
          ],
          "onDelete": "cascade",
          "onUpdate": "no action"
        },
        "applications_job_id_fkey": {
          "name": "applications_job_id_fkey",
          "tableFrom": "applications",
          "tableTo": "jobs",
          "schemaTo": "public",
          "columnsFrom": [
            "job_id"
          ],
          "columnsTo": [
            "id"
          ],
          "onDelete": "cascade",
          "onUpdate": "no action"
        }
      },
      "compositePrimaryKeys": {},
      "uniqueConstraints": {},
      "checkConstraints": {},
      "policies": {},
      "isRLSEnabled": false
    },
    "public.cvs": {
      "name": "cvs",
      "schema": "",
      "columns": {
        "id": {
          "name": "id",
          "type": "uuid",
          "primaryKey": true,
          "notNull": true,
          "default": "gen_random_uuid()"
        },
        "user_id": {
          "name": "user_id",
          "type": "uuid",
          "primaryKey": false,
          "notNull": true
        },
        "name": {
          "name": "name",
          "type": "varchar(255)",
          "primaryKey": false,
          "notNull": true
        },
        "file_path": {
          "name": "file_path",
          "type": "text",
          "primaryKey": false,
          "notNull": true
        },
        "original_filename": {
          "name": "original_filename",
          "type": "varchar(255)",
          "primaryKey": false,
          "notNull": false
        },
        "content_type": {
          "name": "content_type",
          "type": "varchar(255)",
          "primaryKey": false,
          "notNull": false
        },
        "parsed_data": {
          "name": "parsed_data",
          "type": "jsonb",
          "primaryKey": false,
          "notNull": false
        },
        "is_active": {
          "name": "is_active",
          "type": "boolean",
          "primaryKey": false,
          "notNull": false,
          "default": true
        },
        "created_at": {
          "name": "created_at",
          "type": "timestamp(0)",
          "primaryKey": false,
          "notNull": true
        },
        "updated_at": {
          "name": "updated_at",
          "type": "timestamp(0)",
          "primaryKey": false,
          "notNull": true
        }
      },
      "indexes": {
        "cvs_user_id_index": {
          "name": "cvs_user_id_index",
          "columns": [
            {
              "expression": "user_id",
              "asc": true,
              "nulls": "last",
              "opclass": "uuid_ops",
              "isExpression": false
            }
          ],
          "isUnique": false,
          "concurrently": false,
          "method": "btree",
          "with": {}
        }
      },
      "foreignKeys": {
        "cvs_user_id_fkey": {
          "name": "cvs_user_id_fkey",
          "tableFrom": "cvs",
          "tableTo": "users",
          "schemaTo": "public",
          "columnsFrom": [
            "user_id"
          ],
          "columnsTo": [
            "id"
          ],
          "onDelete": "cascade",
          "onUpdate": "no action"
        }
      },
      "compositePrimaryKeys": {},
      "uniqueConstraints": {},
      "checkConstraints": {},
      "policies": {},
      "isRLSEnabled": false
    },
    "public.custom_cvs": {
      "name": "custom_cvs",
      "schema": "",
      "columns": {
        "id": {
          "name": "id",
          "type": "uuid",
          "primaryKey": true,
          "notNull": true,
          "default": "gen_random_uuid()"
        },
        "cv_id": {
          "name": "cv_id",
          "type": "uuid",
          "primaryKey": false,
          "notNull": true
        },
        "job_id": {
          "name": "job_id",
          "type": "uuid",
          "primaryKey": false,
          "notNull": false
        },
        "job_title": {
          "name": "job_title",
          "type": "varchar(255)",
          "primaryKey": false,
          "notNull": false
        },
        "customized_data": {
          "name": "customized_data",
          "type": "jsonb",
          "primaryKey": false,
          "notNull": false
        },
        "cover_letter": {
          "name": "cover_letter",
          "type": "text",
          "primaryKey": false,
          "notNull": false
        },
        "ai_suggestions": {
          "name": "ai_suggestions",
          "type": "jsonb",
          "primaryKey": false,
          "notNull": false
        },
        "created_at": {
          "name": "created_at",
          "type": "timestamp(0)",
          "primaryKey": false,
          "notNull": true
        },
        "updated_at": {
          "name": "updated_at",
          "type": "timestamp(0)",
          "primaryKey": false,
          "notNull": true
        }
      },
      "indexes": {
        "custom_cvs_cv_id_index": {
          "name": "custom_cvs_cv_id_index",
          "columns": [
            {
              "expression": "cv_id",
              "asc": true,
              "nulls": "last",
              "opclass": "uuid_ops",
              "isExpression": false
            }
          ],
          "isUnique": false,
          "concurrently": false,
          "method": "btree",
          "with": {}
        },
        "custom_cvs_job_id_index": {
          "name": "custom_cvs_job_id_index",
          "columns": [
            {
              "expression": "job_id",
              "asc": true,
              "nulls": "last",
              "opclass": "uuid_ops",
              "isExpression": false
            }
          ],
          "isUnique": false,
          "concurrently": false,
          "method": "btree",
          "with": {}
        }
      },
      "foreignKeys": {
        "custom_cvs_cv_id_fkey": {
          "name": "custom_cvs_cv_id_fkey",
          "tableFrom": "custom_cvs",
          "tableTo": "cvs",
          "schemaTo": "public",
          "columnsFrom": [
            "cv_id"
          ],
          "columnsTo": [
            "id"
          ],
          "onDelete": "cascade",
          "onUpdate": "no action"
        },
        "custom_cvs_job_id_fkey": {
          "name": "custom_cvs_job_id_fkey",
          "tableFrom": "custom_cvs",
          "tableTo": "jobs",
          "schemaTo": "public",
          "columnsFrom": [
            "job_id"
          ],
          "columnsTo": [
            "id"
          ],
          "onDelete": "set null",
          "onUpdate": "no action"
        }
      },
      "compositePrimaryKeys": {},
      "uniqueConstraints": {},
      "checkConstraints": {},
      "policies": {},
      "isRLSEnabled": false
    },
    "public.application_queue": {
      "name": "application_queue",
      "schema": "",
      "columns": {
        "id": {
          "name": "id",
          "type": "uuid",
          "primaryKey": true,
          "notNull": true,
          "default": "gen_random_uuid()"
        },
        "workflow_id": {
          "name": "workflow_id",
          "type": "uuid",
          "primaryKey": false,
          "notNull": true
        },
        "user_id": {
          "name": "user_id",
          "type": "uuid",
          "primaryKey": false,
          "notNull": true
        },
        "cv_id": {
          "name": "cv_id",
          "type": "uuid",
          "primaryKey": false,
          "notNull": true
        },
        "job_id": {
          "name": "job_id",
          "type": "uuid",
          "primaryKey": false,
          "notNull": false
        },
        "job_external_id": {
          "name": "job_external_id",
          "type": "varchar(255)",
          "primaryKey": false,
          "notNull": true
        },
        "status": {
          "name": "status",
          "type": "varchar(255)",
          "primaryKey": false,
          "notNull": false,
          "default": "'pending'"
        },
        "payload": {
          "name": "payload",
          "type": "jsonb",
          "primaryKey": false,
          "notNull": false
        },
        "attempts": {
          "name": "attempts",
          "type": "integer",
          "primaryKey": false,
          "notNull": false,
          "default": 0
        },
        "next_run_at": {
          "name": "next_run_at",
          "type": "timestamp(0)",
          "primaryKey": false,
          "notNull": false,
          "default": "now()"
        },
        "priority": {
          "name": "priority",
          "type": "integer",
          "primaryKey": false,
          "notNull": false,
          "default": 0
        },
        "last_error": {
          "name": "last_error",
          "type": "text",
          "primaryKey": false,
          "notNull": false
        },
        "created_at": {
          "name": "created_at",
          "type": "timestamp(0)",
          "primaryKey": false,
          "notNull": true
        },
        "updated_at": {
          "name": "updated_at",
          "type": "timestamp(0)",
          "primaryKey": false,
          "notNull": true
        }
      },
      "indexes": {
        "application_queue_cv_id_index": {
          "name": "application_queue_cv_id_index",
          "columns": [
            {
              "expression": "cv_id",
              "asc": true,
              "nulls": "last",
              "opclass": "uuid_ops",
              "isExpression": false
            }
          ],
          "isUnique": false,
          "concurrently": false,
          "method": "btree",
          "with": {}
        },
        "application_queue_job_id_index": {
          "name": "application_queue_job_id_index",
          "columns": [
            {
              "expression": "job_id",
              "asc": true,
              "nulls": "last",
              "opclass": "uuid_ops",
              "isExpression": false
            }
          ],
          "isUnique": false,
          "concurrently": false,
          "method": "btree",
          "with": {}
        },
        "application_queue_next_run_at_index": {
          "name": "application_queue_next_run_at_index",
          "columns": [
            {
              "expression": "next_run_at",
              "asc": true,
              "nulls": "last",
              "opclass": "timestamp_ops",
              "isExpression": false
            }
          ],
          "isUnique": false,
          "concurrently": false,
          "method": "btree",
          "with": {}
        },
        "application_queue_priority_index": {
          "name": "application_queue_priority_index",
          "columns": [
            {
              "expression": "priority",
              "asc": true,
              "nulls": "last",
              "opclass": "int4_ops",
              "isExpression": false
            }
          ],
          "isUnique": false,
          "concurrently": false,
          "method": "btree",
          "with": {}
        },
        "application_queue_status_index": {
          "name": "application_queue_status_index",
          "columns": [
            {
              "expression": "status",
              "asc": true,
              "nulls": "last",
              "opclass": "text_ops",
              "isExpression": false
            }
          ],
          "isUnique": false,
          "concurrently": false,
          "method": "btree",
          "with": {}
        },
        "application_queue_user_id_index": {
          "name": "application_queue_user_id_index",
          "columns": [
            {
              "expression": "user_id",
              "asc": true,
              "nulls": "last",
              "opclass": "uuid_ops",
              "isExpression": false
            }
          ],
          "isUnique": false,
          "concurrently": false,
          "method": "btree",
          "with": {}
        }
      },
      "foreignKeys": {
        "application_queue_user_id_fkey": {
          "name": "application_queue_user_id_fkey",
          "tableFrom": "application_queue",
          "tableTo": "users",
          "schemaTo": "public",
          "columnsFrom": [
            "user_id"
          ],
          "columnsTo": [
            "id"
          ],
          "onDelete": "cascade",
          "onUpdate": "no action"
        },
        "application_queue_cv_id_fkey": {
          "name": "application_queue_cv_id_fkey",
          "tableFrom": "application_queue",
          "tableTo": "cvs",
          "schemaTo": "public",
          "columnsFrom": [
            "cv_id"
          ],
          "columnsTo": [
            "id"
          ],
          "onDelete": "cascade",
          "onUpdate": "no action"
        },
        "application_queue_job_id_fkey": {
          "name": "application_queue_job_id_fkey",
          "tableFrom": "application_queue",
          "tableTo": "jobs",
          "schemaTo": "public",
          "columnsFrom": [
            "job_id"
          ],
          "columnsTo": [
            "id"
          ],
          "onDelete": "set null",
          "onUpdate": "no action"
        }
      },
      "compositePrimaryKeys": {},
      "uniqueConstraints": {},
      "checkConstraints": {},
      "policies": {},
      "isRLSEnabled": false
    },
    "public.users": {
      "name": "users",
      "schema": "",
      "columns": {
        "id": {
          "name": "id",
          "type": "uuid",
          "primaryKey": true,
          "notNull": true,
          "default": "gen_random_uuid()"
        },
        "email": {
          "name": "email",
          "type": "varchar(255)",
          "primaryKey": false,
          "notNull": true
        },
        "password_hash": {
          "name": "password_hash",
          "type": "varchar(255)",
          "primaryKey": false,
          "notNull": true
        },
        "inserted_at": {
          "name": "inserted_at",
          "type": "timestamp(0)",
          "primaryKey": false,
          "notNull": true
        },
        "updated_at": {
          "name": "updated_at",
          "type": "timestamp(0)",
          "primaryKey": false,
          "notNull": true
        }
      },
      "indexes": {
        "users_email_index": {
          "name": "users_email_index",
          "columns": [
            {
              "expression": "email",
              "asc": true,
              "nulls": "last",
              "opclass": "text_ops",
              "isExpression": false
            }
          ],
          "isUnique": true,
          "concurrently": false,
          "method": "btree",
          "with": {}
        }
      },
      "foreignKeys": {},
      "compositePrimaryKeys": {},
      "uniqueConstraints": {},
      "checkConstraints": {},
      "policies": {},
      "isRLSEnabled": false
    },
    "public.parsed_cvs": {
      "name": "parsed_cvs",
      "schema": "",
      "columns": {
        "id": {
          "name": "id",
          "type": "uuid",
          "primaryKey": true,
          "notNull": true,
          "default": "gen_random_uuid()"
        },
        "user_id": {
          "name": "user_id",
          "type": "uuid",
          "primaryKey": false,
          "notNull": false
        },
        "first_name": {
          "name": "first_name",
          "type": "varchar(100)",
          "primaryKey": false,
          "notNull": false
        },
        "last_name": {
          "name": "last_name",
          "type": "varchar(100)",
          "primaryKey": false,
          "notNull": false
        },
        "email": {
          "name": "email",
          "type": "varchar(255)",
          "primaryKey": false,
          "notNull": false
        },
        "phone": {
          "name": "phone",
          "type": "varchar(50)",
          "primaryKey": false,
          "notNull": false
        },
        "title": {
          "name": "title",
          "type": "varchar(255)",
          "primaryKey": false,
          "notNull": false
        },
        "summary": {
          "name": "summary",
          "type": "text",
          "primaryKey": false,
          "notNull": false
        },
        "experience": {
          "name": "experience",
          "type": "text",
          "primaryKey": false,
          "notNull": false
        },
        "education": {
          "name": "education",
          "type": "text",
          "primaryKey": false,
          "notNull": false
        },
        "skills": {
          "name": "skills",
          "type": "varchar(255)[]",
          "primaryKey": false,
          "notNull": false,
          "default": "'{\"RAY\"}'"
        },
        "projects": {
          "name": "projects",
          "type": "text",
          "primaryKey": false,
          "notNull": false
        },
        "full_text": {
          "name": "full_text",
          "type": "text",
          "primaryKey": false,
          "notNull": false
        },
        "original_filename": {
          "name": "original_filename",
          "type": "varchar(255)",
          "primaryKey": false,
          "notNull": false
        },
        "file_path": {
          "name": "file_path",
          "type": "text",
          "primaryKey": false,
          "notNull": false
        },
        "model_used": {
          "name": "model_used",
          "type": "varchar(100)",
          "primaryKey": false,
          "notNull": false
        },
        "created_at": {
          "name": "created_at",
          "type": "timestamp(0)",
          "primaryKey": false,
          "notNull": true
        },
        "updated_at": {
          "name": "updated_at",
          "type": "timestamp(0)",
          "primaryKey": false,
          "notNull": true
        }
      },
      "indexes": {
        "parsed_cvs_user_id_index": {
          "name": "parsed_cvs_user_id_index",
          "columns": [
            {
              "expression": "user_id",
              "asc": true,
              "nulls": "last",
              "opclass": "uuid_ops",
              "isExpression": false
            }
          ],
          "isUnique": false,
          "concurrently": false,
          "method": "btree",
          "with": {}
        }
      },
      "foreignKeys": {
        "parsed_cvs_user_id_fkey": {
          "name": "parsed_cvs_user_id_fkey",
          "tableFrom": "parsed_cvs",
          "tableTo": "users",
          "schemaTo": "public",
          "columnsFrom": [
            "user_id"
          ],
          "columnsTo": [
            "id"
          ],
          "onDelete": "set null",
          "onUpdate": "no action"
        }
      },
      "compositePrimaryKeys": {},
      "uniqueConstraints": {},
      "checkConstraints": {},
      "policies": {},
      "isRLSEnabled": false
    },
    "public.hh_tokens": {
      "name": "hh_tokens",
      "schema": "",
      "columns": {
        "id": {
          "name": "id",
          "type": "uuid",
          "primaryKey": true,
          "notNull": true
        },
        "user_id": {
          "name": "user_id",
          "type": "uuid",
          "primaryKey": false,
          "notNull": false
        },
        "access_token": {
          "name": "access_token",
          "type": "text",
          "primaryKey": false,
          "notNull": true
        },
        "refresh_token": {
          "name": "refresh_token",
          "type": "text",
          "primaryKey": false,
          "notNull": true
        },
        "expires_at": {
          "name": "expires_at",
          "type": "timestamp(0)",
          "primaryKey": false,
          "notNull": true
        },
        "inserted_at": {
          "name": "inserted_at",
          "type": "timestamp(0)",
          "primaryKey": false,
          "notNull": true
        },
        "updated_at": {
          "name": "updated_at",
          "type": "timestamp(0)",
          "primaryKey": false,
          "notNull": true
        }
      },
      "indexes": {
        "hh_tokens_user_id_index": {
          "name": "hh_tokens_user_id_index",
          "columns": [
            {
              "expression": "user_id",
              "asc": true,
              "nulls": "last",
              "opclass": "uuid_ops",
              "isExpression": false
            }
          ],
          "isUnique": false,
          "concurrently": false,
          "method": "btree",
          "with": {}
        }
      },
      "foreignKeys": {},
      "compositePrimaryKeys": {},
      "uniqueConstraints": {},
      "checkConstraints": {},
      "policies": {},
      "isRLSEnabled": false
    }
  },
  "enums": {},
  "schemas": {},
  "sequences": {},
  "roles": {},
  "policies": {},
  "views": {},
  "_meta": {
    "schemas": {},
    "tables": {},
    "columns": {}
  },
  "internal": {
    "tables": {
      "jobs": {
        "columns": {
          "skills": {
            "isArray": true,
            "dimensions": 1,
            "rawType": "character varying(255)"
          }
        }
      },
      "parsed_cvs": {
        "columns": {
          "skills": {
            "isArray": true,
            "dimensions": 1,
            "rawType": "character varying(255)"
          }
        }
      }
    }
  }
}